redshift_upload/__init__.py
redshift_upload/__main__.py
redshift_upload/base_utilities.py
redshift_upload/column_type_utilities.py
redshift_upload/constants.py
redshift_upload/local_utilities.py
redshift_upload/redshift_utilities.py
redshift_upload/testing_utilities.py
redshift_upload/upload.py
redshift_upload/cli/__init__.py
redshift_upload/cli/show_add_user.py
redshift_upload/cli/show_help.py
redshift_upload/cli/gen_environment/__init__.py
redshift_upload/cli/gen_environment/gen_environment.py
redshift_upload/cli/gen_environment/template.yaml
redshift_upload/credential_store/__init__.py
redshift_upload/credential_store/credential_store.py
redshift_upload/db_interfaces/__init__.py
redshift_upload/db_interfaces/dummy.py
redshift_upload/db_interfaces/redshift.py
redshift_upload/db_interfaces/redshift_queries/competing_conns.sql
redshift_upload/db_interfaces/redshift_queries/copy_table.sql
redshift_upload/db_interfaces/redshift_queries/dependent_views.sql
redshift_upload/db_interfaces/redshift_queries/remote_cols.sql
redshift_upload/db_interfaces/redshift_queries/view_privileges.sql
simple_redshift_upload-1.2.4.dist-info/LICENSE.txt
simple_redshift_upload-1.2.4.dist-info/METADATA
simple_redshift_upload-1.2.4.dist-info/WHEEL
simple_redshift_upload-1.2.4.dist-info/top_level.txt
simple_redshift_upload-1.2.4.dist-info/RECORD
