Metadata-Version: 2.1
Name: simple-redshift-upload
Version: 1.2.4
Summary: A package that simplifies uploading data to redshift
Home-page: https://github.com/mwhamilton/redshift_upload
Download-URL: https://github.com/mwhamilton/redshift_upload/archive/1.2.4.tar.gz
Author: Matthew Hamilton
Author-email: mwhamilton6@gmail.com
License: MIT
Platform: UNKNOWN
Classifier: License :: OSI Approved :: MIT License
Classifier: Programming Language :: Python :: 3
Classifier: Programming Language :: Python :: 3.7
License-File: LICENSE.txt
Requires-Dist: boto3
Requires-Dist: boto3-stubs[s3]
Requires-Dist: click
Requires-Dist: colorama
Requires-Dist: jsonschema
Requires-Dist: pandas
Requires-Dist: psycopg2
Requires-Dist: pytest
Requires-Dist: toposort
